openai_function_tokens/__init__.py
openai_function_tokens/openai_function_tokens.py
openai_function_tokens-0.1.2.dist-info/METADATA
openai_function_tokens-0.1.2.dist-info/WHEEL
openai_function_tokens-0.1.2.dist-info/top_level.txt
openai_function_tokens-0.1.2.dist-info/RECORD
