Metadata-Version: 2.1
Name: openai-function-tokens
Version: 0.1.2
Summary: A package to estimate token counts for messages AND functions in openai's chat completion API.
Home-page: https://github.com/Reversehobo/openai-function-tokens
Author: Reversehobo
Author-email: info@nordicintel.com
Classifier: Programming Language :: Python :: 3
Classifier: License :: OSI Approved :: MIT License
Classifier: Operating System :: OS Independent
Requires-Python: >=3.6
Requires-Dist: tiktoken
